[
  {
    "_id": {
      "$oid": "1"
    },
    "nome": "SILVANA RODRIGUES FONSECA",
    "idaide": "14",
    "cpf": "093.329.233-12"
  },
  {
    "_id": {
      "$oid": "2"
    },
    "nome": "GABRIEL DE ALMEIDA",
    "idaide": "15",
    "cpf": "093.329.233-12"
  },
  {
    "_id": {
      "$oid": "3"
    },
    "nome": "ÍTALO ARAÚJO DE ALMEIDA",
    "idaide": "17",
    "cpf": "000-000-000-00"
  },
  {
    "_id": {
      "$oid": "4"
    },
    "nome": "ANTÔNIO KAUÃ SILVA BARROS",
    "idaide": "14",
    "cpf": "093.329.233-12"
  },
  {
    "_id": {
      "$oid": "5"
    },
    "nome": "SILVANA RODRIGUES FONSECA",
    "idaide": "14",
    "cpf": "093.329.233-12"
  },
  {
    "_id": {
      "$oid": "6"
    },
    "nome": "SILVANA RODRIGUES FONSECA",
    "idaide": "14",
    "cpf": "093.329.233-12"
  },
  {
    "_id": {
      "$oid": "7"
    },
    "nome": "SILVANA RODRIGUES FONSECA",
    "idaide": "14",
    "cpf": "093.329.233-12"
  },
  {
    "_id": {
      "$oid": "8"
    },
    "nome": "SILVANA RODRIGUES FONSECA",
    "idaide": "14",
    "cpf": "093.329.233-12"
  },
  {
    "_id": {
      "$oid": "9"
    },
    "nome": "SILVANA RODRIGUES FONSECA",
    "idaide": "14",
    "cpf": "093.329.233-12"
  },
  {
    "_id": {
      "$oid": "10"
    },
    "nome": "SILVANA RODRIGUES FONSECA",
    "idaide": "14",
    "cpf": "093.329.233-12"
  },
  {
    "_id": {
      "$oid": "11"
    },
    "nome": "SILVANA RODRIGUES FONSECA",
    "idaide": "14",
    "cpf": "093.329.233-12"
  },
  {
    "_id": {
      "$oid": "12"
    },
    "nome": "SILVANA RODRIGUES FONSECA",
    "idaide": "14",
    "cpf": "093.329.233-12"
  },
  {
    "_id": {
      "$oid": "13"
    },
    "nome": "SILVANA RODRIGUES FONSECA",
    "idaide": "14",
    "cpf": "093.329.233-12"
  },
  {
    "_id": {
      "$oid": "14"
    },
    "nome": "SILVANA RODRIGUES FONSECA",
    "idaide": "14",
    "cpf": "093.329.233-12"
  },
  {
    "_id": {
      "$oid": "15"
    },
    "nome": "SILVANA RODRIGUES FONSECA",
    "idaide": "14",
    "cpf": "093.329.233-12"
  },
  {
    "_id": {
      "$oid": "16"
    },
    "nome": "SILVANA RODRIGUES FONSECA",
    "idaide": "14",
    "cpf": "093.329.233-12"
  },
  {
    "_id": {
      "$oid": "17"
    },
    "nome": "SILVANA RODRIGUES FONSECA",
    "idaide": "14",
    "cpf": "093.329.233-12"
  },
  {
    "_id": {
      "$oid": "18"
    },
    "nome": "SILVANA RODRIGUES FONSECA",
    "idaide": "14",
    "cpf": "093.329.233-12"
  },
  {
    "_id": {
      "$oid": "19"
    },
    "nome": "SILVANA RODRIGUES FONSECA",
    "idaide": "14",
    "cpf": "093.329.233-12"
  },
  {
    "_id": {
      "$oid": "20"
    },
    "nome": "SILVANA RODRIGUES FONSECA",
    "idaide": "14",
    "cpf": "093.329.233-12"
  }
] 